scml_vis/__init__.py
scml_vis/__main__.py
scml_vis/cli.py
scml_vis/compiler.py
scml_vis/presenter.py
scml_vis/utils.py
scml_vis/vendor/__init__.py
scml_vis/vendor/quick/LICENSE
scml_vis/vendor/quick/README.md
scml_vis/vendor/quick/__init__.py
scml_vis/vendor/quick/quick.py
scml_vis/vendor/quick/requirements.txt
scml_vis-0.2.11.dist-info/LICENSE
scml_vis-0.2.11.dist-info/METADATA
scml_vis-0.2.11.dist-info/WHEEL
scml_vis-0.2.11.dist-info/entry_points.txt
scml_vis-0.2.11.dist-info/top_level.txt
scml_vis-0.2.11.dist-info/RECORD
