Metadata-Version: 2.1
Name: scml-vis
Version: 0.2.11
Summary: "A simple visualiser for SCML worlds and tournaments"
Home-page: https://github.com/yasserfarouk/negmas
Author-email: yasserfarouk@gmail.com
License: Apache License 2.0
Keywords: negotiation,mas,multi-agent,simulation,AI,negmas,scml,scml-agents
Classifier: License :: OSI Approved :: GNU General Public License v2 or later (GPLv2+)
Classifier: Programming Language :: Python :: 3
Classifier: Programming Language :: Python :: 3.8
Classifier: Programming Language :: Python :: 3.9
Classifier: Programming Language :: Python :: 3.10
Classifier: Programming Language :: Python :: Implementation :: CPython
Requires-Python: >=3.8
License-File: LICENSE
Requires-Dist: Click (>=6.0)
Requires-Dist: numpy
Requires-Dist: pandas
Requires-Dist: seaborn
Requires-Dist: streamlit
Requires-Dist: plotly
Requires-Dist: click
Requires-Dist: click-config-file
Requires-Dist: watchdog
Requires-Dist: datasette-vega
Requires-Dist: csvs-to-sqlite
Requires-Dist: scml
Provides-Extra: dev
Requires-Dist: autoflake ; extra == 'dev'
Requires-Dist: black ; extra == 'dev'
Requires-Dist: isort ; extra == 'dev'
Requires-Dist: mypy ; extra == 'dev'
Requires-Dist: pytest ; extra == 'dev'
Requires-Dist: pytest-cov ; extra == 'dev'
Requires-Dist: pytest-randomly ; extra == 'dev'
Requires-Dist: pytest-sugar ; extra == 'dev'
Requires-Dist: pytest-xdist ; extra == 'dev'
